cli/__init__.py
cli/cli.py
cli/constants.py
gitlab_bk-0.0.1.dist-info/LICENSE
gitlab_bk-0.0.1.dist-info/METADATA
gitlab_bk-0.0.1.dist-info/WHEEL
gitlab_bk-0.0.1.dist-info/entry_points.txt
gitlab_bk-0.0.1.dist-info/top_level.txt
gitlab_bk-0.0.1.dist-info/RECORD
