Metadata-Version: 2.1
Name: gitlab-bk
Version: 0.0.1
Summary: Clone all projects in Gitlab account by group at once.
Home-page: https://github.com/SinaKarimi7/Gitlab-Backup
Author: Cinna Karimi
Author-email: sinakarimi76@gmail.com
License: MIT
Download-URL: https://github.com/SinaKarimi7/Gitlab-Backup/archive/v_01.tar.gz
Keywords: GITLAB,BACKUP,CLONE,SANCTION
Platform: UNKNOWN
Classifier: Intended Audience :: Developers
Classifier: Topic :: System :: Archiving :: Backup
Classifier: License :: OSI Approved :: MIT License
Classifier: Operating System :: OS Independent
Classifier: Programming Language :: Python :: 3
Requires-Python: >=3.6
Requires-Dist: alive-progress (==1.6.1)
